README.rst
setup.py
Vase.egg-info/PKG-INFO
Vase.egg-info/SOURCES.txt
Vase.egg-info/dependency_links.txt
Vase.egg-info/requires.txt
Vase.egg-info/top_level.txt
vase/__init__.py
vase/app.py
vase/exceptions.py
vase/http.py
vase/log.py
vase/request.py
vase/response.py
vase/stream.py
vase/webserver.py
vase/websocket.py