Metadata-Version: 1.1
Name: Vase
Version: 0.1.3
Summary: Async Web framework based on Tulip/asyncio
Home-page: UNKNOWN
Author: Vladimir Kryachko
Author-email: v.kryachko@gmail.com
License: UNKNOWN
Platform: UNKNOWN
Classifier: Programming Language :: Python
Classifier: Programming Language :: Python :: 3
Classifier: Programming Language :: Python :: 3.3
